cram.py
cram-0.6.data/scripts/cram
cram-0.6.dist-info/DESCRIPTION.rst
cram-0.6.dist-info/METADATA
cram-0.6.dist-info/pydist.json
cram-0.6.dist-info/RECORD
cram-0.6.dist-info/top_level.txt
cram-0.6.dist-info/WHEEL
