Metadata-Version: 2.0
Name: cram
Version: 0.6
Summary: A simple testing framework for command line applications
Home-page: https://bitheap.org/cram/
Author: Brodie Rao
Author-email: brodie@bitheap.org
License: GNU GPL
Download-URL: https://bitheap.org/cram/cram-0.6.tar.gz
Keywords: automatic functional test framework
Platform: UNKNOWN
Classifier: Development Status :: 3 - Alpha
Classifier: Environment :: Console
Classifier: Intended Audience :: Developers
Classifier: License :: OSI Approved :: GNU General Public License (GPL)
Classifier: Natural Language :: English
Classifier: Operating System :: OS Independent
Classifier: Programming Language :: Python
Classifier: Programming Language :: Python :: 3
Classifier: Programming Language :: Unix Shell
Classifier: Topic :: Software Development :: Testing
